README.md
setup.cfg
setup.py
mpl_helpers/__init__.py
mpl_helpers/_mpl_helpers.py
mpl_helpers.egg-info/PKG-INFO
mpl_helpers.egg-info/SOURCES.txt
mpl_helpers.egg-info/dependency_links.txt
mpl_helpers.egg-info/requires.txt
mpl_helpers.egg-info/top_level.txt
mpl_helpers.egg-info/zip-safe