Metadata-Version: 1.1
Name: mpl-helpers
Version: 0.1.0
Summary: A Python 3.6 library for tweaking matplotlib figures.
Home-page: https://github.com/clintval/mpl-helpers
Author: clintval
Author-email: valentine.clint@gmail.com
License: MIT
Download-URL: https://github.com/clintval/mpl-helpers/archive/v0.1.0.tar.gz
Platform: UNKNOWN
Classifier: Development Status :: 2 - Pre-Alpha
Classifier: Intended Audience :: Developers
Classifier: Intended Audience :: Science/Research
Classifier: License :: OSI Approved :: MIT License
Classifier: Programming Language :: Python :: 3.6
